j_chess_lib/__init__.py
j_chess_lib/main.py
j_chess_lib/ai/Sample.py
j_chess_lib/ai/__init__.py
j_chess_lib/ai/ai.py
j_chess_lib/ai/container.py
j_chess_lib/ai/board/__init__.py
j_chess_lib/ai/board/utilities.py
j_chess_lib/ai/examples/__init__.py
j_chess_lib/ai/examples/pgn_player.py
j_chess_lib/ai/examples/rng.py
j_chess_lib/client/Client.py
j_chess_lib/client/Exceptions.py
j_chess_lib/client/__init__.py
j_chess_lib/client/match/Game.py
j_chess_lib/client/match/Match.py
j_chess_lib/client/match/__init__.py
j_chess_lib/communication/__init__.py
j_chess_lib/communication/connection/Connection.py
j_chess_lib/communication/connection/__init__.py
j_chess_lib/communication/schema/__init__.py
j_chess_lib/communication/schema/j_chess_message.py
j_chess_lib-0.10.3.dist-info/AUTHORS.rst
j_chess_lib-0.10.3.dist-info/LICENSE
j_chess_lib-0.10.3.dist-info/METADATA
j_chess_lib-0.10.3.dist-info/WHEEL
j_chess_lib-0.10.3.dist-info/top_level.txt
j_chess_lib-0.10.3.dist-info/zip-safe
j_chess_lib-0.10.3.dist-info/RECORD
