Metadata-Version: 2.1
Name: j-chess-lib
Version: 0.10.3
Summary: Python library for a j-chess bot. Beep Boop
Home-page: https://github.com/RedRem95/j_chess_lib
Author: RedRem95
License: GNU General Public License v3
Keywords: j_chess_lib
Platform: UNKNOWN
Classifier: Development Status :: 2 - Pre-Alpha
Classifier: Intended Audience :: Developers
Classifier: License :: OSI Approved :: GNU General Public License v3 (GPLv3)
Classifier: Natural Language :: English
Classifier: Programming Language :: Python :: 3
Classifier: Programming Language :: Python :: 3.6
Classifier: Programming Language :: Python :: 3.7
Classifier: Programming Language :: Python :: 3.8
Classifier: Programming Language :: Python :: 3.9
Requires-Python: >=3.6
License-File: LICENSE
License-File: AUTHORS.rst
Requires-Dist: xsdata[cli,lxml,soap]
